oppe/__init__.py
oppe/config.py
oppe/exceptions.py
oppe/oppe.py
oppe/utils.py
oppe-0.2.3.dist-info/LICENSE
oppe-0.2.3.dist-info/METADATA
oppe-0.2.3.dist-info/WHEEL
oppe-0.2.3.dist-info/top_level.txt
oppe-0.2.3.dist-info/RECORD
