Metadata-Version: 2.1
Name: oppe
Version: 0.2.3
Summary: A Python API Wrapper for Oppe
Home-page: https://github.com/kilobyteno/oppe-for-python
Author: Kilobyte AS
License: MIT
Project-URL: Homepage, https://oppe.app
Project-URL: Documentation, https://docs.oppe.app
Project-URL: Github, https://github.com/kilobyteno/oppe-for-python
Classifier: Programming Language :: Python
Classifier: Programming Language :: Python :: 3
Classifier: Programming Language :: Python :: 3.8
Classifier: Programming Language :: Python :: 3.9
Classifier: Programming Language :: Python :: 3.10
Classifier: Programming Language :: Python :: 3.11
Requires-Python: >=3.8
License-File: LICENSE
Requires-Dist: python-dotenv >=1.0.0
Requires-Dist: requests >=2.31.0
